{"lo": {"recv_bytes": 0, "recv_packets": 0, "recv_errs": 0, "recv_drop": 0, "recv_fifo": 0, "recv_frame": 0, "recv_compressed": 0, "recv_multicast": 0, "trans_bytes": 0, "trans_packets": 0, "trans_errs": 0, "trans_drop": 0, "trans_fifo": 0, "trans_colls": 0, "trans_carrier": 0, "trans_compressed": 0}, "8-0": {"recv_bytes": 12107692, "recv_packets": 139910, "recv_errs": 0, "recv_drop": 0, "recv_fifo": 0, "recv_frame": 0, "recv_compressed": 0, "recv_multicast": 0, "trans_bytes": 14846404, "trans_packets": 171563, "trans_errs": 0, "trans_drop": 0, "trans_fifo": 0, "trans_colls": 0, "trans_carrier": 0, "trans_compressed": 0}, "8-1": {"recv_bytes": 2778, "recv_packets": 31, "recv_errs": 0, "recv_drop": 0, "recv_fifo": 0, "recv_frame": 0, "recv_compressed": 0, "recv_multicast": 0, "trans_bytes": 3593386, "trans_packets": 41583, "trans_errs": 0, "trans_drop": 0, "trans_fifo": 0, "trans_colls": 0, "trans_carrier": 0, "trans_compressed": 0}, "8-2": {"recv_bytes": 7573833997, "recv_packets": 550419, "recv_errs": 0, "recv_drop": 0, "recv_fifo": 0, "recv_frame": 0, "recv_compressed": 0, "recv_multicast": 0, "trans_bytes": 3800887502, "trans_packets": 387208, "trans_errs": 0, "trans_drop": 0, "trans_fifo": 0, "trans_colls": 0, "trans_carrier": 0, "trans_compressed": 0}}