{"lo": {"recv_bytes": 0, "recv_packets": 0, "recv_errs": 0, "recv_drop": 0, "recv_fifo": 0, "recv_frame": 0, "recv_compressed": 0, "recv_multicast": 0, "trans_bytes": 0, "trans_packets": 0, "trans_errs": 0, "trans_drop": 0, "trans_fifo": 0, "trans_colls": 0, "trans_carrier": 0, "trans_compressed": 0}, "1-0": {"recv_bytes": 3885106962, "recv_packets": 829242, "recv_errs": 0, "recv_drop": 6619, "recv_fifo": 0, "recv_frame": 0, "recv_compressed": 0, "recv_multicast": 0, "trans_bytes": 10769426, "trans_packets": 120919, "trans_errs": 0, "trans_drop": 923, "trans_fifo": 0, "trans_colls": 0, "trans_carrier": 0, "trans_compressed": 0}, "1-1": {"recv_bytes": 520, "recv_packets": 4, "recv_errs": 0, "recv_drop": 0, "recv_fifo": 0, "recv_frame": 0, "recv_compressed": 0, "recv_multicast": 0, "trans_bytes": 756, "trans_packets": 6, "trans_errs": 0, "trans_drop": 0, "trans_fifo": 0, "trans_colls": 0, "trans_carrier": 0, "trans_compressed": 0}, "1-2": {"recv_bytes": 14146364, "recv_packets": 157496, "recv_errs": 0, "recv_drop": 820, "recv_fifo": 0, "recv_frame": 0, "recv_compressed": 0, "recv_multicast": 0, "trans_bytes": 3515135317, "trans_packets": 727808, "trans_errs": 0, "trans_drop": 4053, "trans_fifo": 0, "trans_colls": 0, "trans_carrier": 0, "trans_compressed": 0}, "1-3": {"recv_bytes": 18293708, "recv_packets": 204768, "recv_errs": 0, "recv_drop": 1452, "recv_fifo": 0, "recv_frame": 0, "recv_compressed": 0, "recv_multicast": 0, "trans_bytes": 3870416146, "trans_packets": 824036, "trans_errs": 0, "trans_drop": 5203, "trans_fifo": 0, "trans_colls": 0, "trans_carrier": 0, "trans_compressed": 0}}