{"lo": {"recv_bytes": 0, "recv_packets": 0, "recv_errs": 0, "recv_drop": 0, "recv_fifo": 0, "recv_frame": 0, "recv_compressed": 0, "recv_multicast": 0, "trans_bytes": 0, "trans_packets": 0, "trans_errs": 0, "trans_drop": 0, "trans_fifo": 0, "trans_colls": 0, "trans_carrier": 0, "trans_compressed": 0}, "4-0": {"recv_bytes": 11626300, "recv_packets": 134362, "recv_errs": 0, "recv_drop": 0, "recv_fifo": 0, "recv_frame": 0, "recv_compressed": 0, "recv_multicast": 0, "trans_bytes": 1787928344, "trans_packets": 263417, "trans_errs": 0, "trans_drop": 0, "trans_fifo": 0, "trans_colls": 0, "trans_carrier": 0, "trans_compressed": 0}, "4-1": {"recv_bytes": 3795593286, "recv_packets": 349229, "recv_errs": 0, "recv_drop": 0, "recv_fifo": 0, "recv_frame": 0, "recv_compressed": 0, "recv_multicast": 0, "trans_bytes": 4751135, "trans_packets": 54831, "trans_errs": 0, "trans_drop": 0, "trans_fifo": 0, "trans_colls": 0, "trans_carrier": 0, "trans_compressed": 0}, "4-2": {"recv_bytes": 992, "recv_packets": 8, "recv_errs": 0, "recv_drop": 0, "recv_fifo": 0, "recv_frame": 0, "recv_compressed": 0, "recv_multicast": 0, "trans_bytes": 992, "trans_packets": 8, "trans_errs": 0, "trans_drop": 0, "trans_fifo": 0, "trans_colls": 0, "trans_carrier": 0, "trans_compressed": 0}, "4-3": {"recv_bytes": 4054002, "recv_packets": 46955, "recv_errs": 0, "recv_drop": 0, "recv_fifo": 0, "recv_frame": 0, "recv_compressed": 0, "recv_multicast": 0, "trans_bytes": 2764, "trans_packets": 30, "trans_errs": 0, "trans_drop": 0, "trans_fifo": 0, "trans_colls": 0, "trans_carrier": 0, "trans_compressed": 0}, "4-4": {"recv_bytes": 13926313, "recv_packets": 160862, "recv_errs": 0, "recv_drop": 0, "recv_fifo": 0, "recv_frame": 0, "recv_compressed": 0, "recv_multicast": 0, "trans_bytes": 11626300, "trans_packets": 134362, "trans_errs": 0, "trans_drop": 0, "trans_fifo": 0, "trans_colls": 0, "trans_carrier": 0, "trans_compressed": 0}, "4-5": {"recv_bytes": 1783877178, "recv_packets": 216492, "recv_errs": 0, "recv_drop": 0, "recv_fifo": 0, "recv_frame": 0, "recv_compressed": 0, "recv_multicast": 0, "trans_bytes": 7580153980, "trans_packets": 600257, "trans_errs": 0, "trans_drop": 0, "trans_fifo": 0, "trans_colls": 0, "trans_carrier": 0, "trans_compressed": 0}}