{"lo": {"recv_bytes": 0, "recv_packets": 0, "recv_errs": 0, "recv_drop": 0, "recv_fifo": 0, "recv_frame": 0, "recv_compressed": 0, "recv_multicast": 0, "trans_bytes": 0, "trans_packets": 0, "trans_errs": 0, "trans_drop": 0, "trans_fifo": 0, "trans_colls": 0, "trans_carrier": 0, "trans_compressed": 0}, "0-0": {"recv_bytes": 1006, "recv_packets": 9, "recv_errs": 0, "recv_drop": 0, "recv_fifo": 0, "recv_frame": 0, "recv_compressed": 0, "recv_multicast": 0, "trans_bytes": 1159717234, "trans_packets": 224195, "trans_errs": 0, "trans_drop": 0, "trans_fifo": 0, "trans_colls": 0, "trans_carrier": 0, "trans_compressed": 0}, "0-1": {"recv_bytes": 21825937, "recv_packets": 251275, "recv_errs": 0, "recv_drop": 0, "recv_fifo": 0, "recv_frame": 0, "recv_compressed": 0, "recv_multicast": 0, "trans_bytes": 380408662, "trans_packets": 46399, "trans_errs": 0, "trans_drop": 0, "trans_fifo": 0, "trans_colls": 0, "trans_carrier": 0, "trans_compressed": 0}, "0-2": {"recv_bytes": 380408426, "recv_packets": 46397, "recv_errs": 0, "recv_drop": 0, "recv_fifo": 0, "recv_frame": 0, "recv_compressed": 0, "recv_multicast": 0, "trans_bytes": 3894440, "trans_packets": 44989, "trans_errs": 0, "trans_drop": 0, "trans_fifo": 0, "trans_colls": 0, "trans_carrier": 0, "trans_compressed": 0}, "0-3": {"recv_bytes": 383539641, "recv_packets": 53750, "recv_errs": 0, "recv_drop": 0, "recv_fifo": 0, "recv_frame": 0, "recv_compressed": 0, "recv_multicast": 0, "trans_bytes": 4526530, "trans_packets": 52188, "trans_errs": 0, "trans_drop": 0, "trans_fifo": 0, "trans_colls": 0, "trans_carrier": 0, "trans_compressed": 0}, "0-4": {"recv_bytes": 386160262, "recv_packets": 72151, "recv_errs": 0, "recv_drop": 0, "recv_fifo": 0, "recv_frame": 0, "recv_compressed": 0, "recv_multicast": 0, "trans_bytes": 5901544, "trans_packets": 67921, "trans_errs": 0, "trans_drop": 0, "trans_fifo": 0, "trans_colls": 0, "trans_carrier": 0, "trans_compressed": 0}, "0-5": {"recv_bytes": 390020309, "recv_packets": 98321, "recv_errs": 0, "recv_drop": 0, "recv_fifo": 0, "recv_frame": 0, "recv_compressed": 0, "recv_multicast": 0, "trans_bytes": 7506871, "trans_packets": 86209, "trans_errs": 0, "trans_drop": 0, "trans_fifo": 0, "trans_colls": 0, "trans_carrier": 0, "trans_compressed": 0}}