{"lo": {"recv_bytes": 0, "recv_packets": 0, "recv_errs": 0, "recv_drop": 0, "recv_fifo": 0, "recv_frame": 0, "recv_compressed": 0, "recv_multicast": 0, "trans_bytes": 0, "trans_packets": 0, "trans_errs": 0, "trans_drop": 0, "trans_fifo": 0, "trans_colls": 0, "trans_carrier": 0, "trans_compressed": 0}, "0-0": {"recv_bytes": 1092, "recv_packets": 10, "recv_errs": 0, "recv_drop": 0, "recv_fifo": 0, "recv_frame": 0, "recv_compressed": 0, "recv_multicast": 0, "trans_bytes": 1148551522, "trans_packets": 168616, "trans_errs": 0, "trans_drop": 0, "trans_fifo": 0, "trans_colls": 0, "trans_carrier": 0, "trans_compressed": 0}, "0-1": {"recv_bytes": 17738179, "recv_packets": 205169, "recv_errs": 0, "recv_drop": 0, "recv_fifo": 0, "recv_frame": 0, "recv_compressed": 0, "recv_multicast": 0, "trans_bytes": 379300389, "trans_packets": 43662, "trans_errs": 0, "trans_drop": 0, "trans_fifo": 0, "trans_colls": 0, "trans_carrier": 0, "trans_compressed": 0}, "0-2": {"recv_bytes": 379300239, "recv_packets": 43661, "recv_errs": 0, "recv_drop": 0, "recv_fifo": 0, "recv_frame": 0, "recv_compressed": 0, "recv_multicast": 0, "trans_bytes": 3698689, "trans_packets": 42793, "trans_errs": 0, "trans_drop": 0, "trans_fifo": 0, "trans_colls": 0, "trans_carrier": 0, "trans_compressed": 0}, "0-3": {"recv_bytes": 381457169, "recv_packets": 45994, "recv_errs": 0, "recv_drop": 0, "recv_fifo": 0, "recv_frame": 0, "recv_compressed": 0, "recv_multicast": 0, "trans_bytes": 3900671, "trans_packets": 45112, "trans_errs": 0, "trans_drop": 0, "trans_fifo": 0, "trans_colls": 0, "trans_carrier": 0, "trans_compressed": 0}, "0-4": {"recv_bytes": 382515788, "recv_packets": 53652, "recv_errs": 0, "recv_drop": 0, "recv_fifo": 0, "recv_frame": 0, "recv_compressed": 0, "recv_multicast": 0, "trans_bytes": 4482645, "trans_packets": 51837, "trans_errs": 0, "trans_drop": 0, "trans_fifo": 0, "trans_colls": 0, "trans_carrier": 0, "trans_compressed": 0}, "0-5": {"recv_bytes": 384581221, "recv_packets": 68994, "recv_errs": 0, "recv_drop": 0, "recv_fifo": 0, "recv_frame": 0, "recv_compressed": 0, "recv_multicast": 0, "trans_bytes": 5659772, "trans_packets": 65460, "trans_errs": 0, "trans_drop": 0, "trans_fifo": 0, "trans_colls": 0, "trans_carrier": 0, "trans_compressed": 0}}